grid/__init__.py
grid/metadata.py
grid/cli/__init__.py
grid/cli/__main__.py
grid/cli/client.py
grid/cli/exceptions.py
grid/cli/rich_click.py
grid/cli/sdk_record.py
grid/cli/types.py
grid/cli/utilities.py
grid/cli/autocomplete/__init__.py
grid/cli/autocomplete/complete.bash
grid/cli/autocomplete/complete.zsh
grid/cli/cli/__init__.py
grid/cli/cli/grid_artifacts.py
grid/cli/cli/grid_clusters.py
grid/cli/cli/grid_credentials.py
grid/cli/cli/grid_datastore.py
grid/cli/cli/grid_delete.py
grid/cli/cli/grid_edit.py
grid/cli/cli/grid_env.py
grid/cli/cli/grid_history.py
grid/cli/cli/grid_instance_type.py
grid/cli/cli/grid_login.py
grid/cli/cli/grid_logs.py
grid/cli/cli/grid_run.py
grid/cli/cli/grid_session.py
grid/cli/cli/grid_ssh_keys.py
grid/cli/cli/grid_status.py
grid/cli/cli/grid_stop.py
grid/cli/cli/grid_team.py
grid/cli/cli/grid_user.py
grid/cli/cli/grid_view.py
grid/cli/cli/utilities.py
grid/cli/cli/tui/__init__.py
grid/cli/cli/tui/serializer.py
grid/cli/commands/__init__.py
grid/cli/commands/checks.py
grid/cli/commands/dependencies.py
grid/cli/core/__init__.py
grid/cli/core/artifact.py
grid/cli/core/base.py
grid/cli/core/callbacks.py
grid/cli/core/experiment.py
grid/cli/core/formatter.py
grid/cli/core/run.py
grid/cli/core/team.py
grid/cli/observables/__init__.py
grid/cli/observables/base.py
grid/cli/observables/experiment.py
grid/cli/observables/interactive_node.py
grid/cli/observables/run.py
grid/openapi/__init__.py
grid/openapi/api_client.py
grid/openapi/configuration.py
grid/openapi/rest.py
grid/openapi/api/__init__.py
grid/openapi/api/auth_service_api.py
grid/openapi/api/billing_service_api.py
grid/openapi/api/cluster_service_api.py
grid/openapi/api/config_service_api.py
grid/openapi/api/credential_service_api.py
grid/openapi/api/datastore_service_api.py
grid/openapi/api/experiment_service_api.py
grid/openapi/api/run_service_api.py
grid/openapi/api/saml_organizations_service_api.py
grid/openapi/api/session_service_api.py
lightning_grid-0.8.81.dist-info/METADATA
lightning_grid-0.8.81.dist-info/WHEEL
lightning_grid-0.8.81.dist-info/entry_points.txt
lightning_grid-0.8.81.dist-info/top_level.txt
lightning_grid-0.8.81.dist-info/RECORD
