Metadata-Version: 2.1
Name: lightning-grid
Version: 0.8.81
Summary: Grid Python SDK.
Home-page: https://grid.ai
Author: Grid AI Engineering
Author-email: grid-eng@grid.ai
Classifier: Programming Language :: Python
Classifier: Programming Language :: Python :: 3.8
Classifier: Programming Language :: Python :: 3.9
Classifier: Programming Language :: Python :: 3.10
Requires-Python: >=3.8.0
Requires-Dist: arrow
Requires-Dist: click
Requires-Dist: dataclasses-json
Requires-Dist: gql[all] (<4.0.0,>=3.0.0a4)
Requires-Dist: humanize (<4.0.0,>=3.0)
Requires-Dist: marshmallow
Requires-Dist: packaging (>=20.7)
Requires-Dist: pipreqs
Requires-Dist: python-dateutil
Requires-Dist: pytz
Requires-Dist: PyYAML (<6.0,>=5.0)
Requires-Dist: requests (<3.0.0,>=2.24)
Requires-Dist: requests-toolbelt (<1.0.0,>=0.9.1)
Requires-Dist: rich (>=10.2)
Requires-Dist: tqdm (<5.0.0,>=4.0)
Requires-Dist: ujson
Requires-Dist: ulid-py
Requires-Dist: urllib3 (<2.0.0,>=1.26)
Requires-Dist: validators
Requires-Dist: websocket-client (==1.2.1)
Requires-Dist: websockets (<10.0,>=9.0)
Requires-Dist: yaspin (<1.0.0,>=0.16)
